nxpy/__init__.py
nxpy/misc.py
nxpy/subprocess.py
nxpy/version.py
niu2x_py-1.1.1.dist-info/LICENSE
niu2x_py-1.1.1.dist-info/METADATA
niu2x_py-1.1.1.dist-info/WHEEL
niu2x_py-1.1.1.dist-info/top_level.txt
niu2x_py-1.1.1.dist-info/RECORD
