Metadata-Version: 2.1
Name: niu2x-py
Version: 1.1.1
Summary: niu2x's python library
Home-page: https://gitee.com/niu2x/nxpy
Author: niu2x
Author-email: niu2x@icloud.com
Project-URL: Bug Tracker, https://gitee.com/niu2x/nxpy/issues
Classifier: Programming Language :: Python :: 3
Classifier: License :: OSI Approved :: MIT License
Classifier: Operating System :: OS Independent
Requires-Python: >=3.6
License-File: LICENSE
